{
    "managed-datasets": [
	{
	    "source": {
		"remote-host": "olympus",
		"pool": "o-nas",
		"dataset": "zam/tmp_source",
		"windows": [
		    {"max-age": {"minutes": 2}, "period": {"seconds": 10}},
		    {"max-age": {"minutes": 5}, "period": {"minutes": 1}}
		]
	    },
	    "destinations": [
		{
		    "remote-host": "olympus",
		    "pool": "o-nas",
		    "dataset": "zam/tmp_dest",
		    "windows": [
			{"period": {"minutes": 5}}
		    ]
		}
	    ],
	    "snapshot-period": {"seconds": "10"},
	    "replication-period": {"minutes": "1"},
	    "prune-period": {"minutes": "1"}
	}
    ]
}
